api_paginator
