Metadata-Version: 2.1
Name: django-easy-paginate
Version: 0.0.4
Summary: A django package for paginating api responses
Home-page: https://github.com/ejasmuhamed/django-easy-paginate
Author: Ejas Muhammed
Author-email: ejasmuhamed@gmail.com.com
License: UNKNOWN
Platform: UNKNOWN
Classifier: Programming Language :: Python :: 3
Classifier: License :: OSI Approved :: MIT License
Classifier: Operating System :: OS Independent
Requires-Python: >=3.0
